django_socket_framework/__init__.py
django_socket_framework/consumers.py
django_socket_framework/method_lists.py
django_socket_framework/middlewares.py
django_socket_framework/types.py
django_socket_framework/utils.py
django_socket_framework/auth/__init__.py
django_socket_framework/auth/consumers.py
django_socket_framework/auth/event_lists.py
django_socket_framework/auth/middlewares.py
django_socket_framework/auth/types.py
django_socket_framework-0.1.9.dist-info/LICENSE
django_socket_framework-0.1.9.dist-info/METADATA
django_socket_framework-0.1.9.dist-info/WHEEL
django_socket_framework-0.1.9.dist-info/top_level.txt
django_socket_framework-0.1.9.dist-info/RECORD
