Metadata-Version: 2.1
Name: django-socket-framework
Version: 0.1.9
Summary: Socket consumer environment with more systematic methods/events and auth
Author: Lia Va
License: UNKNOWN
Platform: UNKNOWN
Classifier: Programming Language :: Python :: 3.8
Classifier: Programming Language :: Python :: 3.9
Classifier: Programming Language :: Python :: 3.10
Classifier: License :: OSI Approved :: MIT License
Classifier: Operating System :: OS Independent
Requires-Python: >=3.8
License-File: LICENSE
